{
    "%vlocity_namespace%__AdditionalInformation__c": "B2B Express(GT1) - Create Working Cart Cart (record Type) Quote based on Sales Quote.",
    "%vlocity_namespace%__CustomJavaScript__c": "create_WorkingCart_SampleInput.json",
    "%vlocity_namespace%__DisableMetadataCache__c": false,
    "%vlocity_namespace%__ElementTypeToHTMLTemplateList__c": "{\"ElementTypeToHTMLTemplateList\":[]}",
    "%vlocity_namespace%__Element__c": [
        "create_WorkingCart_Element_getSalesQuoteDetails.json",
        "create_WorkingCart_Element_RecordTypeCB.json",
        "create_WorkingCart_Element_SVRecordType.json",
        "create_WorkingCart_Element_GetRecordTypeId.json",
        "create_WorkingCart_Element_CreateWorkingCart.json",
        "create_WorkingCart_Element_CopyDiscounts.json",
        "create_WorkingCart_Element_ResponseAction1.json"
    ],
    "%vlocity_namespace%__IsLwcEnabled__c": false,
    "%vlocity_namespace%__IsProcedure__c": true,
    "%vlocity_namespace%__IsReusable__c": false,
    "%vlocity_namespace%__IsTest__c": false,
    "%vlocity_namespace%__Language__c": "Procedure",
    "%vlocity_namespace%__OmniProcessType__c": "Integration Procedure",
    "%vlocity_namespace%__ProcedureKey__c": "create_WorkingCart",
    "%vlocity_namespace%__PropertySet__c": "create_WorkingCart_PropertySet.json",
    "%vlocity_namespace%__SubType__c": "WorkingCart",
    "%vlocity_namespace%__Type__c": "create",
    "Name": "CreateWorkingCartQuote",
    "VlocityDataPackType": "SObject",
    "VlocityRecordSObjectType": "%vlocity_namespace%__OmniScript__c",
    "VlocityRecordSourceKey": "%vlocity_namespace%__OmniScript__c/create/WorkingCart/Procedure"
}