{
    "CurrencyIsoCode": "INR",
    "IsActive": true,
    "IsOmniScriptEmbeddable": false,
    "Name": "ResponseAction4",
    "OmniProcessId": {
        "Name": "CPQGetCartsProducts",
        "VlocityDataPackType": "VlocityMatchingKeyObject",
        "VlocityMatchingRecordSourceKey": "OmniProcess/CPQ/GetCartsProducts/Procedure",
        "VlocityRecordSObjectType": "OmniProcess"
    },
    "ParentElementId": {
        "Name": "noProducts",
        "OmniProcessId": {
            "Name": "CPQGetCartsProducts",
            "VlocityDataPackType": "VlocityMatchingKeyObject",
            "VlocityMatchingRecordSourceKey": "OmniProcess/CPQ/GetCartsProducts/Procedure",
            "VlocityRecordSObjectType": "OmniProcess"
        },
        "VlocityDataPackType": "VlocityMatchingKeyObject",
        "VlocityMatchingRecordSourceKey": "OmniProcessElement/OmniProcess/CPQ/GetCartsProducts/Procedure/noProducts",
        "VlocityRecordSObjectType": "OmniProcessElement"
    },
    "ParentElementName": "noProducts",
    "ParentElementType": "Conditional Block",
    "PropertySetConfig": {
        "additionalOutput": {
            "data": "%ListAction2%",
            "productsSize": "%getCartsProducts:totalSize%",
            "promotionsSize": "%getCartsPromotions:totalSize%"
        },
        "disOnTplt": false,
        "executionConditionalFormula": "",
        "label": "ResponseAction1",
        "responseDefaultData": {
        },
        "responseFormat": "JSON",
        "responseJSONNode": "",
        "responseJSONPath": "",
        "returnFullDataJSON": false,
        "returnOnlyAdditionalOutput": false,
        "sendJSONNode": "",
        "sendJSONPath": "",
        "show": null,
        "useFormulas": true,
        "vlcResponseHeaders": {
        }
    },
    "Type": "Response Action",
    "VlocityDataPackType": "SObject",
    "VlocityRecordSObjectType": "OmniProcessElement",
    "VlocityRecordSourceKey": "OmniProcessElement/OmniProcess/CPQ/GetCartsProducts/Procedure/ResponseAction4"
}