[
    {
        "%vlocity_namespace%__ActionParameters__c": "{\"ATT_IPV6_REQUIRED\":{\"actionsList\":[{\"action\":\"DISABLE\",\"value\":false}],\"index\":0},\"ATT_LAN_IPV4_SUBNET_MASK\":{\"actionsList\":[{\"action\":\"DISABLE\",\"value\":true},{\"action\":\"ASSIGN\",\"value\":\"Not Applicable\"}],\"index\":1},\"ATT_LAN_IPV6_SUBNET_MASK\":{\"actionsList\":[{\"action\":\"DISABLE\",\"value\":false}],\"index\":2}}",
        "%vlocity_namespace%__AddMode__c": "",
        "%vlocity_namespace%__AttributeModificationContext__c": "Bundle",
        "%vlocity_namespace%__Context__c": "Bundle",
        "%vlocity_namespace%__DefaultQuantity__c": 1,
        "%vlocity_namespace%__Description__c": "",
        "%vlocity_namespace%__Family__c": "",
        "%vlocity_namespace%__GlobalKey__c": "31791c8d-8447-8e96-ce91-fa6948c2fd70",
        "%vlocity_namespace%__IsConditional__c": true,
        "%vlocity_namespace%__MaxQuantity__c": 999,
        "%vlocity_namespace%__MinQuantity__c": 1,
        "%vlocity_namespace%__ObjectTypeId__c": "",
        "%vlocity_namespace%__Product2Id__c": {
            "%vlocity_namespace%__GlobalKey__c": "2bb854d6-f8a0-d673-e046-f9bec9d30748",
            "VlocityDataPackType": "VlocityMatchingKeyObject",
            "VlocityMatchingRecordSourceKey": "Product2/2bb854d6-f8a0-d673-e046-f9bec9d30748",
            "VlocityRecordSObjectType": "Product2"
        },
        "%vlocity_namespace%__ProductGroupKey__c": "9ff14f25-9f55-4421-12fd-019ba6856aa7",
        "%vlocity_namespace%__RelatedObjectTypeId__c": "",
        "%vlocity_namespace%__RelatedProductFilterId__c": "",
        "%vlocity_namespace%__RelatedProductGroupKey__c": "78e75aed-6af9-0649-05d2-cbd80ae4f4db",
        "%vlocity_namespace%__RelatedProductId__c": {
            "%vlocity_namespace%__GlobalKey__c": "9375f81e-09c5-ca49-68a4-bd92344a9ae2",
            "VlocityDataPackType": "VlocityLookupMatchingKeyObject",
            "VlocityLookupRecordSourceKey": "Product2/9375f81e-09c5-ca49-68a4-bd92344a9ae2",
            "VlocityRecordSObjectType": "Product2"
        },
        "%vlocity_namespace%__RelationshipType__c": "Modify Attributes",
        "%vlocity_namespace%__ReverseMaxQuantity__c": "",
        "%vlocity_namespace%__ReverseMinQuantity__c": "",
        "CurrencyIsoCode": "INR",
        "Name": "EILL Primary Link iConnectivity LAN Attribute Modification IPv6",
        "VlocityDataPackType": "SObject",
        "VlocityRecordSObjectType": "%vlocity_namespace%__ProductRelationship__c",
        "VlocityRecordSourceKey": "%vlocity_namespace%__ProductRelationship__c/31791c8d-8447-8e96-ce91-fa6948c2fd70"
    },
    {
        "%vlocity_namespace%__ActionParameters__c": "{\"ATT_IPV6_REQUIRED\":{\"actionsList\":[{\"action\":\"ASSIGN\",\"value\":false},{\"action\":\"DISABLE\",\"value\":true}],\"index\":0},\"ATT_LAN_IPV4_SUBNET_MASK\":{\"actionsList\":[{\"action\":\"DISABLE\",\"value\":false}],\"index\":1},\"ATT_LAN_IPV6_SUBNET_MASK\":{\"actionsList\":[{\"action\":\"ASSIGN\",\"value\":\"Not Applicable\"},{\"action\":\"DISABLE\",\"value\":true}],\"index\":2}}",
        "%vlocity_namespace%__AddMode__c": "",
        "%vlocity_namespace%__AttributeModificationContext__c": "Bundle",
        "%vlocity_namespace%__Context__c": "Bundle",
        "%vlocity_namespace%__DefaultQuantity__c": 1,
        "%vlocity_namespace%__Description__c": "",
        "%vlocity_namespace%__Family__c": "",
        "%vlocity_namespace%__GlobalKey__c": "6edc084d-d1e3-9116-3574-b75ad7eaeb31",
        "%vlocity_namespace%__IsConditional__c": true,
        "%vlocity_namespace%__MaxQuantity__c": 999,
        "%vlocity_namespace%__MinQuantity__c": 1,
        "%vlocity_namespace%__ObjectTypeId__c": "",
        "%vlocity_namespace%__Product2Id__c": {
            "%vlocity_namespace%__GlobalKey__c": "2bb854d6-f8a0-d673-e046-f9bec9d30748",
            "VlocityDataPackType": "VlocityMatchingKeyObject",
            "VlocityMatchingRecordSourceKey": "Product2/2bb854d6-f8a0-d673-e046-f9bec9d30748",
            "VlocityRecordSObjectType": "Product2"
        },
        "%vlocity_namespace%__ProductGroupKey__c": "9ff14f25-9f55-4421-12fd-019ba6856aa7",
        "%vlocity_namespace%__RelatedObjectTypeId__c": "",
        "%vlocity_namespace%__RelatedProductFilterId__c": "",
        "%vlocity_namespace%__RelatedProductGroupKey__c": "78e75aed-6af9-0649-05d2-cbd80ae4f4db",
        "%vlocity_namespace%__RelatedProductId__c": {
            "%vlocity_namespace%__GlobalKey__c": "9375f81e-09c5-ca49-68a4-bd92344a9ae2",
            "VlocityDataPackType": "VlocityLookupMatchingKeyObject",
            "VlocityLookupRecordSourceKey": "Product2/9375f81e-09c5-ca49-68a4-bd92344a9ae2",
            "VlocityRecordSObjectType": "Product2"
        },
        "%vlocity_namespace%__RelationshipType__c": "Modify Attributes",
        "%vlocity_namespace%__ReverseMaxQuantity__c": "",
        "%vlocity_namespace%__ReverseMinQuantity__c": "",
        "CurrencyIsoCode": "INR",
        "Name": "EILL Primary Link iConnectivity LAN Attribute Modification IPv4",
        "VlocityDataPackType": "SObject",
        "VlocityRecordSObjectType": "%vlocity_namespace%__ProductRelationship__c",
        "VlocityRecordSourceKey": "%vlocity_namespace%__ProductRelationship__c/6edc084d-d1e3-9116-3574-b75ad7eaeb31"
    },
    {
        "%vlocity_namespace%__ActionParameters__c": "{\"ATT_ROUTING_TYPE\":{\"actionsList\":[{\"action\":\"DISABLE\",\"value\":false}],\"index\":0}}",
        "%vlocity_namespace%__AddMode__c": "",
        "%vlocity_namespace%__AttributeModificationContext__c": "Bundle",
        "%vlocity_namespace%__Context__c": "Bundle",
        "%vlocity_namespace%__DefaultQuantity__c": 1,
        "%vlocity_namespace%__Description__c": "",
        "%vlocity_namespace%__Family__c": "",
        "%vlocity_namespace%__GlobalKey__c": "76e69c23-6fdf-c241-75dd-2ae43e76ae5a",
        "%vlocity_namespace%__IsConditional__c": true,
        "%vlocity_namespace%__MaxQuantity__c": 999,
        "%vlocity_namespace%__MinQuantity__c": 1,
        "%vlocity_namespace%__ObjectTypeId__c": "",
        "%vlocity_namespace%__Product2Id__c": {
            "%vlocity_namespace%__GlobalKey__c": "2bb854d6-f8a0-d673-e046-f9bec9d30748",
            "VlocityDataPackType": "VlocityMatchingKeyObject",
            "VlocityMatchingRecordSourceKey": "Product2/2bb854d6-f8a0-d673-e046-f9bec9d30748",
            "VlocityRecordSObjectType": "Product2"
        },
        "%vlocity_namespace%__ProductGroupKey__c": "9ff14f25-9f55-4421-12fd-019ba6856aa7",
        "%vlocity_namespace%__RelatedObjectTypeId__c": "",
        "%vlocity_namespace%__RelatedProductFilterId__c": "",
        "%vlocity_namespace%__RelatedProductGroupKey__c": "f53fa2d5-d1cf-e801-d04f-dd7429d4a371",
        "%vlocity_namespace%__RelatedProductId__c": {
            "%vlocity_namespace%__GlobalKey__c": "419222ac-2e88-7ce5-ffe8-49ea37ad7b1e",
            "VlocityDataPackType": "VlocityLookupMatchingKeyObject",
            "VlocityLookupRecordSourceKey": "Product2/419222ac-2e88-7ce5-ffe8-49ea37ad7b1e",
            "VlocityRecordSObjectType": "Product2"
        },
        "%vlocity_namespace%__RelationshipType__c": "Modify Attributes",
        "%vlocity_namespace%__ReverseMaxQuantity__c": "",
        "%vlocity_namespace%__ReverseMinQuantity__c": "",
        "CurrencyIsoCode": "INR",
        "Name": "EILL Primary Link Service Type Not As Unmanaged Attribute Modify Routing Type",
        "VlocityDataPackType": "SObject",
        "VlocityRecordSObjectType": "%vlocity_namespace%__ProductRelationship__c",
        "VlocityRecordSourceKey": "%vlocity_namespace%__ProductRelationship__c/76e69c23-6fdf-c241-75dd-2ae43e76ae5a"
    },
    {
        "%vlocity_namespace%__ActionParameters__c": "{\"ATT_WAN_IPV6_CE_SUBNET_MASK\":{\"actionsList\":[{\"action\":\"ASSIGN\",\"value\":\"Not Applicable\"},{\"action\":\"DISABLE\",\"value\":true}],\"index\":0},\"ATT_WAN_IPV6_PE_SUBNET_MASK\":{\"actionsList\":[{\"action\":\"ASSIGN\",\"value\":\"Not Applicable\"},{\"action\":\"DISABLE\",\"value\":true}],\"index\":1},\"ATT_IPV6_REQUIRED\":{\"actionsList\":[{\"action\":\"ASSIGN\",\"value\":false},{\"action\":\"DISABLE\",\"value\":true}],\"index\":2},\"ATT_WAN_IPV4_CE_SUBNET_MASK\":{\"actionsList\":[{\"action\":\"DISABLE\",\"value\":false}],\"index\":3},\"ATT_WAN_IPV4_PE_SUBNET_MASK\":{\"actionsList\":[{\"action\":\"DISABLE\",\"value\":false}],\"index\":4}}",
        "%vlocity_namespace%__AddMode__c": "",
        "%vlocity_namespace%__AttributeModificationContext__c": "Bundle",
        "%vlocity_namespace%__Context__c": "Bundle",
        "%vlocity_namespace%__DefaultQuantity__c": 1,
        "%vlocity_namespace%__Description__c": "",
        "%vlocity_namespace%__Family__c": "",
        "%vlocity_namespace%__GlobalKey__c": "8a7b9e51-1c84-7a26-a7a3-d5869f8a333d",
        "%vlocity_namespace%__IsConditional__c": true,
        "%vlocity_namespace%__MaxQuantity__c": 999,
        "%vlocity_namespace%__MinQuantity__c": 1,
        "%vlocity_namespace%__ObjectTypeId__c": "",
        "%vlocity_namespace%__Product2Id__c": {
            "%vlocity_namespace%__GlobalKey__c": "2bb854d6-f8a0-d673-e046-f9bec9d30748",
            "VlocityDataPackType": "VlocityMatchingKeyObject",
            "VlocityMatchingRecordSourceKey": "Product2/2bb854d6-f8a0-d673-e046-f9bec9d30748",
            "VlocityRecordSObjectType": "Product2"
        },
        "%vlocity_namespace%__ProductGroupKey__c": "9ff14f25-9f55-4421-12fd-019ba6856aa7",
        "%vlocity_namespace%__RelatedObjectTypeId__c": "",
        "%vlocity_namespace%__RelatedProductFilterId__c": "",
        "%vlocity_namespace%__RelatedProductGroupKey__c": "0ed7b367-8bcc-b0f1-4eb9-73c3d16d39bc",
        "%vlocity_namespace%__RelatedProductId__c": {
            "%vlocity_namespace%__GlobalKey__c": "616eeb08-fad3-a550-3493-9602f9d2318e",
            "VlocityDataPackType": "VlocityLookupMatchingKeyObject",
            "VlocityLookupRecordSourceKey": "Product2/616eeb08-fad3-a550-3493-9602f9d2318e",
            "VlocityRecordSObjectType": "Product2"
        },
        "%vlocity_namespace%__RelationshipType__c": "Modify Attributes",
        "%vlocity_namespace%__ReverseMaxQuantity__c": "",
        "%vlocity_namespace%__ReverseMinQuantity__c": "",
        "CurrencyIsoCode": "INR",
        "Name": "EILL Primary Link iConnectivity WAN Attribute Modification IPv4",
        "VlocityDataPackType": "SObject",
        "VlocityRecordSObjectType": "%vlocity_namespace%__ProductRelationship__c",
        "VlocityRecordSourceKey": "%vlocity_namespace%__ProductRelationship__c/8a7b9e51-1c84-7a26-a7a3-d5869f8a333d"
    },
    {
        "%vlocity_namespace%__ActionParameters__c": "{\"ATT_ROUTING_TYPE\":{\"actionsList\":[{\"action\":\"ASSIGN\",\"value\":\"None\"}],\"index\":0}}",
        "%vlocity_namespace%__AddMode__c": "asChild",
        "%vlocity_namespace%__AttributeModificationContext__c": "Bundle",
        "%vlocity_namespace%__Context__c": "Bundle",
        "%vlocity_namespace%__DefaultQuantity__c": 1,
        "%vlocity_namespace%__Description__c": "If(Service Type == 'Unmanaged'), then Routing Type Should be None.",
        "%vlocity_namespace%__Family__c": "",
        "%vlocity_namespace%__GlobalKey__c": "a5c18436-847a-7366-262d-2b8f139cfb36",
        "%vlocity_namespace%__IsConditional__c": true,
        "%vlocity_namespace%__MaxQuantity__c": 1,
        "%vlocity_namespace%__MinQuantity__c": 1,
        "%vlocity_namespace%__ObjectTypeId__c": "",
        "%vlocity_namespace%__Product2Id__c": {
            "%vlocity_namespace%__GlobalKey__c": "2bb854d6-f8a0-d673-e046-f9bec9d30748",
            "VlocityDataPackType": "VlocityMatchingKeyObject",
            "VlocityMatchingRecordSourceKey": "Product2/2bb854d6-f8a0-d673-e046-f9bec9d30748",
            "VlocityRecordSObjectType": "Product2"
        },
        "%vlocity_namespace%__ProductGroupKey__c": "9ff14f25-9f55-4421-12fd-019ba6856aa7",
        "%vlocity_namespace%__RelatedObjectTypeId__c": "",
        "%vlocity_namespace%__RelatedProductFilterId__c": "",
        "%vlocity_namespace%__RelatedProductGroupKey__c": "f53fa2d5-d1cf-e801-d04f-dd7429d4a371",
        "%vlocity_namespace%__RelatedProductId__c": {
            "%vlocity_namespace%__GlobalKey__c": "419222ac-2e88-7ce5-ffe8-49ea37ad7b1e",
            "VlocityDataPackType": "VlocityLookupMatchingKeyObject",
            "VlocityLookupRecordSourceKey": "Product2/419222ac-2e88-7ce5-ffe8-49ea37ad7b1e",
            "VlocityRecordSObjectType": "Product2"
        },
        "%vlocity_namespace%__RelationshipType__c": "Modify Attributes",
        "%vlocity_namespace%__ReverseMaxQuantity__c": "",
        "%vlocity_namespace%__ReverseMinQuantity__c": "",
        "CurrencyIsoCode": "INR",
        "Name": "Primary Link Modify Attribute iConnectivity Router Type = None",
        "VlocityDataPackType": "SObject",
        "VlocityRecordSObjectType": "%vlocity_namespace%__ProductRelationship__c",
        "VlocityRecordSourceKey": "%vlocity_namespace%__ProductRelationship__c/a5c18436-847a-7366-262d-2b8f139cfb36"
    },
    {
        "%vlocity_namespace%__ActionParameters__c": "",
        "%vlocity_namespace%__AddMode__c": "asChild",
        "%vlocity_namespace%__AttributeModificationContext__c": "",
        "%vlocity_namespace%__Context__c": "Cart",
        "%vlocity_namespace%__DefaultQuantity__c": 1,
        "%vlocity_namespace%__Description__c": "",
        "%vlocity_namespace%__Family__c": "",
        "%vlocity_namespace%__GlobalKey__c": "dd5fa753-5a6b-45fb-fece-ef39329e7fd3",
        "%vlocity_namespace%__IsConditional__c": true,
        "%vlocity_namespace%__MaxQuantity__c": 1,
        "%vlocity_namespace%__MinQuantity__c": 0,
        "%vlocity_namespace%__ObjectTypeId__c": "",
        "%vlocity_namespace%__Product2Id__c": {
            "%vlocity_namespace%__GlobalKey__c": "2bb854d6-f8a0-d673-e046-f9bec9d30748",
            "VlocityDataPackType": "VlocityMatchingKeyObject",
            "VlocityMatchingRecordSourceKey": "Product2/2bb854d6-f8a0-d673-e046-f9bec9d30748",
            "VlocityRecordSObjectType": "Product2"
        },
        "%vlocity_namespace%__ProductGroupKey__c": "9ff14f25-9f55-4421-12fd-019ba6856aa7",
        "%vlocity_namespace%__RelatedObjectTypeId__c": "",
        "%vlocity_namespace%__RelatedProductFilterId__c": "",
        "%vlocity_namespace%__RelatedProductGroupKey__c": "ab8948cc-0189-7a87-10d3-711461e062ba",
        "%vlocity_namespace%__RelatedProductId__c": {
            "%vlocity_namespace%__GlobalKey__c": "0511e97f-bf3d-c233-6712-66027fa5984e",
            "VlocityDataPackType": "VlocityLookupMatchingKeyObject",
            "VlocityLookupRecordSourceKey": "Product2/0511e97f-bf3d-c233-6712-66027fa5984e",
            "VlocityRecordSObjectType": "Product2"
        },
        "%vlocity_namespace%__RelationshipType__c": "ReliesOn",
        "%vlocity_namespace%__ReverseMaxQuantity__c": "",
        "%vlocity_namespace%__ReverseMinQuantity__c": "",
        "CurrencyIsoCode": "INR",
        "Name": "Third Party Relies On Primary Link",
        "VlocityDataPackType": "SObject",
        "VlocityRecordSObjectType": "%vlocity_namespace%__ProductRelationship__c",
        "VlocityRecordSourceKey": "%vlocity_namespace%__ProductRelationship__c/dd5fa753-5a6b-45fb-fece-ef39329e7fd3"
    },
    {
        "%vlocity_namespace%__ActionParameters__c": "{\"ATT_ROUTING_TYPE\":{\"actionsList\":[{\"action\":\"ASSIGN\",\"value\":\"None\"},{\"action\":\"DISABLE\",\"value\":true}],\"index\":0}}",
        "%vlocity_namespace%__AddMode__c": "",
        "%vlocity_namespace%__AttributeModificationContext__c": "Bundle",
        "%vlocity_namespace%__Context__c": "Bundle",
        "%vlocity_namespace%__DefaultQuantity__c": 1,
        "%vlocity_namespace%__Description__c": "",
        "%vlocity_namespace%__Family__c": "",
        "%vlocity_namespace%__GlobalKey__c": "ea494db7-411e-06c2-50d3-0f24800fb37d",
        "%vlocity_namespace%__IsConditional__c": true,
        "%vlocity_namespace%__MaxQuantity__c": 999,
        "%vlocity_namespace%__MinQuantity__c": 1,
        "%vlocity_namespace%__ObjectTypeId__c": "",
        "%vlocity_namespace%__Product2Id__c": {
            "%vlocity_namespace%__GlobalKey__c": "2bb854d6-f8a0-d673-e046-f9bec9d30748",
            "VlocityDataPackType": "VlocityMatchingKeyObject",
            "VlocityMatchingRecordSourceKey": "Product2/2bb854d6-f8a0-d673-e046-f9bec9d30748",
            "VlocityRecordSObjectType": "Product2"
        },
        "%vlocity_namespace%__ProductGroupKey__c": "9ff14f25-9f55-4421-12fd-019ba6856aa7",
        "%vlocity_namespace%__RelatedObjectTypeId__c": "",
        "%vlocity_namespace%__RelatedProductFilterId__c": "",
        "%vlocity_namespace%__RelatedProductGroupKey__c": "f53fa2d5-d1cf-e801-d04f-dd7429d4a371",
        "%vlocity_namespace%__RelatedProductId__c": {
            "%vlocity_namespace%__GlobalKey__c": "419222ac-2e88-7ce5-ffe8-49ea37ad7b1e",
            "VlocityDataPackType": "VlocityLookupMatchingKeyObject",
            "VlocityLookupRecordSourceKey": "Product2/419222ac-2e88-7ce5-ffe8-49ea37ad7b1e",
            "VlocityRecordSObjectType": "Product2"
        },
        "%vlocity_namespace%__RelationshipType__c": "Modify Attributes",
        "%vlocity_namespace%__ReverseMaxQuantity__c": "",
        "%vlocity_namespace%__ReverseMinQuantity__c": "",
        "CurrencyIsoCode": "INR",
        "Name": "EILL Primary Link Service Type As Unmanaged Attribute Modify Routing Type",
        "VlocityDataPackType": "SObject",
        "VlocityRecordSObjectType": "%vlocity_namespace%__ProductRelationship__c",
        "VlocityRecordSourceKey": "%vlocity_namespace%__ProductRelationship__c/ea494db7-411e-06c2-50d3-0f24800fb37d"
    },
    {
        "%vlocity_namespace%__ActionParameters__c": "{\"ATT_IPV6_REQUIRED\":{\"actionsList\":[{\"action\":\"DISABLE\",\"value\":false}],\"index\":0},\"ATT_WAN_IPV4_CE_SUBNET_MASK\":{\"actionsList\":[{\"action\":\"ASSIGN\",\"value\":\"Not Applicable\"},{\"action\":\"DISABLE\",\"value\":true}],\"index\":1},\"ATT_WAN_IPV4_PE_SUBNET_MASK\":{\"actionsList\":[{\"action\":\"ASSIGN\",\"value\":\"Not Applicable\"},{\"action\":\"DISABLE\",\"value\":true}],\"index\":2},\"ATT_WAN_IPV6_CE_SUBNET_MASK\":{\"actionsList\":[{\"action\":\"DISABLE\",\"value\":false}],\"index\":3},\"ATT_WAN_IPV6_PE_SUBNET_MASK\":{\"actionsList\":[{\"action\":\"DISABLE\",\"value\":false}],\"index\":4}}",
        "%vlocity_namespace%__AddMode__c": "",
        "%vlocity_namespace%__AttributeModificationContext__c": "Bundle",
        "%vlocity_namespace%__Context__c": "Bundle",
        "%vlocity_namespace%__DefaultQuantity__c": 1,
        "%vlocity_namespace%__Description__c": "",
        "%vlocity_namespace%__Family__c": "",
        "%vlocity_namespace%__GlobalKey__c": "f5dcef9d-1df6-145c-a019-1a61b87a6387",
        "%vlocity_namespace%__IsConditional__c": true,
        "%vlocity_namespace%__MaxQuantity__c": 999,
        "%vlocity_namespace%__MinQuantity__c": 1,
        "%vlocity_namespace%__ObjectTypeId__c": "",
        "%vlocity_namespace%__Product2Id__c": {
            "%vlocity_namespace%__GlobalKey__c": "2bb854d6-f8a0-d673-e046-f9bec9d30748",
            "VlocityDataPackType": "VlocityMatchingKeyObject",
            "VlocityMatchingRecordSourceKey": "Product2/2bb854d6-f8a0-d673-e046-f9bec9d30748",
            "VlocityRecordSObjectType": "Product2"
        },
        "%vlocity_namespace%__ProductGroupKey__c": "9ff14f25-9f55-4421-12fd-019ba6856aa7",
        "%vlocity_namespace%__RelatedObjectTypeId__c": "",
        "%vlocity_namespace%__RelatedProductFilterId__c": "",
        "%vlocity_namespace%__RelatedProductGroupKey__c": "0ed7b367-8bcc-b0f1-4eb9-73c3d16d39bc",
        "%vlocity_namespace%__RelatedProductId__c": {
            "%vlocity_namespace%__GlobalKey__c": "616eeb08-fad3-a550-3493-9602f9d2318e",
            "VlocityDataPackType": "VlocityLookupMatchingKeyObject",
            "VlocityLookupRecordSourceKey": "Product2/616eeb08-fad3-a550-3493-9602f9d2318e",
            "VlocityRecordSObjectType": "Product2"
        },
        "%vlocity_namespace%__RelationshipType__c": "Modify Attributes",
        "%vlocity_namespace%__ReverseMaxQuantity__c": "",
        "%vlocity_namespace%__ReverseMinQuantity__c": "",
        "CurrencyIsoCode": "INR",
        "Name": "EILL Primary Link iConnectivity WAN Attribute Modification IPv6",
        "VlocityDataPackType": "SObject",
        "VlocityRecordSObjectType": "%vlocity_namespace%__ProductRelationship__c",
        "VlocityRecordSourceKey": "%vlocity_namespace%__ProductRelationship__c/f5dcef9d-1df6-145c-a019-1a61b87a6387"
    }
]