{
    "ataMigrationPlans": {
        "fieldsMetadata": [
            {
                "nm": "Name"
            },
            {
                "cd": "Code"
            },
            {
                "met": "Method"
            }
        ],
        "response": null
    },
    "soMigrationPlans": {
        "fieldsMetadata": [
            {
                "nm": "Name"
            },
            {
                "cd": "Code"
            },
            {
                "met": "Method"
            }
        ],
        "response": [
            {
                "met": "Specific Offers",
                "nm": "Specific Offer 5155"
            }
        ]
    }
}