[
    {
        "%vlocity_namespace%__ActiveFlg__c": true,
        "%vlocity_namespace%__ApplicableToAllRecords__c": false,
        "%vlocity_namespace%__ApplicableToEntity__c": "",
        "%vlocity_namespace%__AttributeCategoryCode__c": "VEPC_ATTRIBUTE_CATEGORY_SHIPPING_DETAILS",
        "%vlocity_namespace%__AttributeCategoryId__c": {
            "%vlocity_namespace%__Code__c": "VEPC_ATTRIBUTE_CATEGORY_SHIPPING_DETAILS",
            "VlocityDataPackType": "VlocityMatchingKeyObject",
            "VlocityMatchingRecordSourceKey": "%vlocity_namespace%__AttributeCategory__c/VEPC_ATTRIBUTE_CATEGORY_SHIPPING_DETAILS",
            "VlocityRecordSObjectType": "%vlocity_namespace%__AttributeCategory__c"
        },
        "%vlocity_namespace%__AttributeCategoryName__c": "Shipping Details",
        "%vlocity_namespace%__AttributeGroupType__c": "",
        "%vlocity_namespace%__Code__c": "CH_EXPIRY_PERIOD",
        "%vlocity_namespace%__Configurable__c": true,
        "%vlocity_namespace%__CopyMode__c": "",
        "%vlocity_namespace%__CustomConfigUiTemplate__c": "",
        "%vlocity_namespace%__Description__c": "CH_EXPIRY_PERIOD",
        "%vlocity_namespace%__DesignTime__c": "",
        "%vlocity_namespace%__DisplaySequence__c": 1,
        "%vlocity_namespace%__EditMode__c": "",
        "%vlocity_namespace%__EffectiveFromDate__c": "",
        "%vlocity_namespace%__EffectiveUntilDate__c": "",
        "%vlocity_namespace%__ExcludeFromBasketCache__c": false,
        "%vlocity_namespace%__Filterable__c": true,
        "%vlocity_namespace%__GlobalKey__c": "3590d9c1-29c6-e66d-64d9-4c44715e63aa",
        "%vlocity_namespace%__HelpText__c": "",
        "%vlocity_namespace%__IsCloneable__c": true,
        "%vlocity_namespace%__IsEncrypted__c": false,
        "%vlocity_namespace%__IsNotAssetizable__c": false,
        "%vlocity_namespace%__IsPrivate__c": false,
        "%vlocity_namespace%__Overridable__c": "",
        "%vlocity_namespace%__OwnerId__c": "",
        "%vlocity_namespace%__PicklistId__c": "",
        "%vlocity_namespace%__RunTime__c": "",
        "%vlocity_namespace%__UniqueNameField__c": "",
        "%vlocity_namespace%__ValueType__c": "Text",
        "%vlocity_namespace%__Value__c": "",
        "%vlocity_namespace%__isDefaultHidden__c": false,
        "ARTL_IsTechnical__c": false,
        "CurrencyIsoCode": "INR",
        "Name": "Expiry Period",
        "VlocityDataPackType": "SObject",
        "VlocityRecordSObjectType": "%vlocity_namespace%__Attribute__c",
        "VlocityRecordSourceKey": "%vlocity_namespace%__Attribute__c/CH_EXPIRY_PERIOD"
    },
    {
        "%vlocity_namespace%__ActiveFlg__c": true,
        "%vlocity_namespace%__ApplicableToAllRecords__c": false,
        "%vlocity_namespace%__ApplicableToEntity__c": "",
        "%vlocity_namespace%__AttributeCategoryCode__c": "VEPC_ATTRIBUTE_CATEGORY_SHIPPING_DETAILS",
        "%vlocity_namespace%__AttributeCategoryId__c": {
            "%vlocity_namespace%__Code__c": "VEPC_ATTRIBUTE_CATEGORY_SHIPPING_DETAILS",
            "VlocityDataPackType": "VlocityMatchingKeyObject",
            "VlocityMatchingRecordSourceKey": "%vlocity_namespace%__AttributeCategory__c/VEPC_ATTRIBUTE_CATEGORY_SHIPPING_DETAILS",
            "VlocityRecordSObjectType": "%vlocity_namespace%__AttributeCategory__c"
        },
        "%vlocity_namespace%__AttributeCategoryName__c": "Shipping Details",
        "%vlocity_namespace%__AttributeGroupType__c": "",
        "%vlocity_namespace%__Code__c": "CH_MAX_NUMBER",
        "%vlocity_namespace%__Configurable__c": true,
        "%vlocity_namespace%__CopyMode__c": "",
        "%vlocity_namespace%__CustomConfigUiTemplate__c": "",
        "%vlocity_namespace%__Description__c": "CH_MAX_NUMBER",
        "%vlocity_namespace%__DesignTime__c": "",
        "%vlocity_namespace%__DisplaySequence__c": 1,
        "%vlocity_namespace%__EditMode__c": "",
        "%vlocity_namespace%__EffectiveFromDate__c": "",
        "%vlocity_namespace%__EffectiveUntilDate__c": "",
        "%vlocity_namespace%__ExcludeFromBasketCache__c": false,
        "%vlocity_namespace%__Filterable__c": true,
        "%vlocity_namespace%__GlobalKey__c": "ed71a0d3-b3c4-0c56-49c7-ffea5e548f6b",
        "%vlocity_namespace%__HelpText__c": "",
        "%vlocity_namespace%__IsCloneable__c": true,
        "%vlocity_namespace%__IsEncrypted__c": false,
        "%vlocity_namespace%__IsNotAssetizable__c": false,
        "%vlocity_namespace%__IsPrivate__c": false,
        "%vlocity_namespace%__Overridable__c": "",
        "%vlocity_namespace%__OwnerId__c": "",
        "%vlocity_namespace%__PicklistId__c": "",
        "%vlocity_namespace%__RunTime__c": "",
        "%vlocity_namespace%__UniqueNameField__c": "",
        "%vlocity_namespace%__ValueType__c": "Text",
        "%vlocity_namespace%__Value__c": "",
        "%vlocity_namespace%__isDefaultHidden__c": false,
        "ARTL_IsTechnical__c": false,
        "CurrencyIsoCode": "INR",
        "Name": "Max Number",
        "VlocityDataPackType": "SObject",
        "VlocityRecordSObjectType": "%vlocity_namespace%__Attribute__c",
        "VlocityRecordSourceKey": "%vlocity_namespace%__Attribute__c/CH_MAX_NUMBER"
    },
    {
        "%vlocity_namespace%__ActiveFlg__c": true,
        "%vlocity_namespace%__ApplicableToAllRecords__c": false,
        "%vlocity_namespace%__ApplicableToEntity__c": "",
        "%vlocity_namespace%__AttributeCategoryCode__c": "VEPC_ATTRIBUTE_CATEGORY_SHIPPING_DETAILS",
        "%vlocity_namespace%__AttributeCategoryId__c": {
            "%vlocity_namespace%__Code__c": "VEPC_ATTRIBUTE_CATEGORY_SHIPPING_DETAILS",
            "VlocityDataPackType": "VlocityMatchingKeyObject",
            "VlocityMatchingRecordSourceKey": "%vlocity_namespace%__AttributeCategory__c/VEPC_ATTRIBUTE_CATEGORY_SHIPPING_DETAILS",
            "VlocityRecordSObjectType": "%vlocity_namespace%__AttributeCategory__c"
        },
        "%vlocity_namespace%__AttributeCategoryName__c": "Shipping Details",
        "%vlocity_namespace%__AttributeGroupType__c": "",
        "%vlocity_namespace%__Code__c": "CH_USERLANG",
        "%vlocity_namespace%__Configurable__c": true,
        "%vlocity_namespace%__CopyMode__c": "",
        "%vlocity_namespace%__CustomConfigUiTemplate__c": "",
        "%vlocity_namespace%__Description__c": "CH_USERLANG",
        "%vlocity_namespace%__DesignTime__c": "",
        "%vlocity_namespace%__DisplaySequence__c": 1,
        "%vlocity_namespace%__EditMode__c": "",
        "%vlocity_namespace%__EffectiveFromDate__c": "",
        "%vlocity_namespace%__EffectiveUntilDate__c": "",
        "%vlocity_namespace%__ExcludeFromBasketCache__c": false,
        "%vlocity_namespace%__Filterable__c": true,
        "%vlocity_namespace%__GlobalKey__c": "4af504cb-a0d3-c0a1-4155-b269d5f175e4",
        "%vlocity_namespace%__HelpText__c": "",
        "%vlocity_namespace%__IsCloneable__c": true,
        "%vlocity_namespace%__IsEncrypted__c": false,
        "%vlocity_namespace%__IsNotAssetizable__c": false,
        "%vlocity_namespace%__IsPrivate__c": false,
        "%vlocity_namespace%__Overridable__c": "",
        "%vlocity_namespace%__OwnerId__c": "",
        "%vlocity_namespace%__PicklistId__c": "",
        "%vlocity_namespace%__RunTime__c": "",
        "%vlocity_namespace%__UniqueNameField__c": "",
        "%vlocity_namespace%__ValueType__c": "Text",
        "%vlocity_namespace%__Value__c": "",
        "%vlocity_namespace%__isDefaultHidden__c": false,
        "ARTL_IsTechnical__c": false,
        "CurrencyIsoCode": "INR",
        "Name": "User Language",
        "VlocityDataPackType": "SObject",
        "VlocityRecordSObjectType": "%vlocity_namespace%__Attribute__c",
        "VlocityRecordSourceKey": "%vlocity_namespace%__Attribute__c/CH_USERLANG"
    }
]