{
    "CurrencyIsoCode": "INR",
    "IsActive": true,
    "IsOmniScriptEmbeddable": false,
    "Name": "CreateGroups",
    "OmniProcessId": {
        "Name": "CPQ_StartBulkCreateGroups",
        "VlocityDataPackType": "VlocityMatchingKeyObject",
        "VlocityMatchingRecordSourceKey": "OmniProcess/CPQ/StartBulkCreateGroups/Procedure",
        "VlocityRecordSObjectType": "OmniProcess"
    },
    "PropertySetConfig": {
        "actionMessage": "",
        "additionalChainableResponse": {
        },
        "additionalInput": {
            "cartType": "%createCartData:cartType%",
            "contextId": "=IF(createCartData:cartType == \"Quote\", %SetCartId:quoteId%, %SetCartId:orderId%)",
            "groupsToCreate": "=LIST(%GetGroupsToBeCreated:groupsToCreate%)"
        },
        "additionalOutput": {
        },
        "chainOnStep": false,
        "disOnTplt": false,
        "executionConditionalFormula": "createGroupsAsync != true",
        "failOnStepError": true,
        "failureConditionalFormula": "",
        "failureResponse": {
        },
        "label": "RemoteAction1",
        "remoteClass": "MultiServiceAppHandler",
        "remoteMethod": "createGroups",
        "remoteOptions": {
        },
        "responseJSONNode": "",
        "responseJSONPath": "",
        "returnOnlyAdditionalOutput": false,
        "returnOnlyFailureResponse": false,
        "sendJSONNode": "",
        "sendJSONPath": "",
        "sendOnlyAdditionalInput": true,
        "show": null,
        "useFormulas": true
    },
    "Type": "Remote Action",
    "VlocityDataPackType": "SObject",
    "VlocityRecordSObjectType": "OmniProcessElement",
    "VlocityRecordSourceKey": "OmniProcessElement/OmniProcess/CPQ/StartBulkCreateGroups/Procedure/CreateGroups"
}