[
    {
        "%vlocity_namespace%__Abbreviation__c": "",
        "%vlocity_namespace%__BooleanValue__c": false,
        "%vlocity_namespace%__Code__c": "COM-PLV-EVC-TYPE-MTM",
        "%vlocity_namespace%__DateTimeValue__c": "",
        "%vlocity_namespace%__DateValue__c": "",
        "%vlocity_namespace%__EffectiveFromDate__c": "",
        "%vlocity_namespace%__EffectiveUntilDate__c": "",
        "%vlocity_namespace%__GlobalKey__c": "20aefd16-90cd-062b-c40d-0349ca58430c",
        "%vlocity_namespace%__IsActive__c": true,
        "%vlocity_namespace%__IsDefault__c": false,
        "%vlocity_namespace%__NumberValue__c": "",
        "%vlocity_namespace%__PicklistId__c": {
            "%vlocity_namespace%__GlobalKey__c": "c8cc7d8d-7f6e-136b-9a02-1770d3302ffe",
            "VlocityDataPackType": "VlocityMatchingKeyObject",
            "VlocityMatchingRecordSourceKey": "%vlocity_namespace%__Picklist__c/c8cc7d8d-7f6e-136b-9a02-1770d3302ffe",
            "VlocityRecordSObjectType": "%vlocity_namespace%__Picklist__c"
        },
        "%vlocity_namespace%__Sequence__c": 2,
        "%vlocity_namespace%__TextValue__c": "Multipoint-to-Multipoint",
        "%vlocity_namespace%__UnitOfMeasureName__c": "",
        "%vlocity_namespace%__Value__c": "Multipoint-to-Multipoint",
        "CurrencyIsoCode": "INR",
        "Name": "Multipoint-to-Multipoint",
        "VlocityDataPackType": "SObject",
        "VlocityRecordSObjectType": "%vlocity_namespace%__PicklistValue__c",
        "VlocityRecordSourceKey": "%vlocity_namespace%__PicklistValue__c/20aefd16-90cd-062b-c40d-0349ca58430c"
    },
    {
        "%vlocity_namespace%__Abbreviation__c": "",
        "%vlocity_namespace%__BooleanValue__c": false,
        "%vlocity_namespace%__Code__c": "COM-PLV-EVC-TYPE-PTP",
        "%vlocity_namespace%__DateTimeValue__c": "",
        "%vlocity_namespace%__DateValue__c": "",
        "%vlocity_namespace%__EffectiveFromDate__c": "",
        "%vlocity_namespace%__EffectiveUntilDate__c": "",
        "%vlocity_namespace%__GlobalKey__c": "5b25e35c-e539-f911-67a4-b8eefb008f9c",
        "%vlocity_namespace%__IsActive__c": true,
        "%vlocity_namespace%__IsDefault__c": false,
        "%vlocity_namespace%__NumberValue__c": "",
        "%vlocity_namespace%__PicklistId__c": {
            "%vlocity_namespace%__GlobalKey__c": "c8cc7d8d-7f6e-136b-9a02-1770d3302ffe",
            "VlocityDataPackType": "VlocityMatchingKeyObject",
            "VlocityMatchingRecordSourceKey": "%vlocity_namespace%__Picklist__c/c8cc7d8d-7f6e-136b-9a02-1770d3302ffe",
            "VlocityRecordSObjectType": "%vlocity_namespace%__Picklist__c"
        },
        "%vlocity_namespace%__Sequence__c": 1,
        "%vlocity_namespace%__TextValue__c": "Point-to-Point",
        "%vlocity_namespace%__UnitOfMeasureName__c": "",
        "%vlocity_namespace%__Value__c": "Point-to-Point",
        "CurrencyIsoCode": "INR",
        "Name": "Point-to-Point",
        "VlocityDataPackType": "SObject",
        "VlocityRecordSObjectType": "%vlocity_namespace%__PicklistValue__c",
        "VlocityRecordSourceKey": "%vlocity_namespace%__PicklistValue__c/5b25e35c-e539-f911-67a4-b8eefb008f9c"
    },
    {
        "%vlocity_namespace%__Abbreviation__c": "",
        "%vlocity_namespace%__BooleanValue__c": false,
        "%vlocity_namespace%__Code__c": "COM-PLV-EVC-TYPE-RM",
        "%vlocity_namespace%__DateTimeValue__c": "",
        "%vlocity_namespace%__DateValue__c": "",
        "%vlocity_namespace%__EffectiveFromDate__c": "",
        "%vlocity_namespace%__EffectiveUntilDate__c": "",
        "%vlocity_namespace%__GlobalKey__c": "94b3c3e7-6b1b-f00b-eabc-3490b7b372c2",
        "%vlocity_namespace%__IsActive__c": true,
        "%vlocity_namespace%__IsDefault__c": false,
        "%vlocity_namespace%__NumberValue__c": "",
        "%vlocity_namespace%__PicklistId__c": {
            "%vlocity_namespace%__GlobalKey__c": "c8cc7d8d-7f6e-136b-9a02-1770d3302ffe",
            "VlocityDataPackType": "VlocityMatchingKeyObject",
            "VlocityMatchingRecordSourceKey": "%vlocity_namespace%__Picklist__c/c8cc7d8d-7f6e-136b-9a02-1770d3302ffe",
            "VlocityRecordSObjectType": "%vlocity_namespace%__Picklist__c"
        },
        "%vlocity_namespace%__Sequence__c": 3,
        "%vlocity_namespace%__TextValue__c": "Rooted-Multipoint",
        "%vlocity_namespace%__UnitOfMeasureName__c": "",
        "%vlocity_namespace%__Value__c": "Rooted-Multipoint",
        "CurrencyIsoCode": "INR",
        "Name": "Rooted-Multipoint",
        "VlocityDataPackType": "SObject",
        "VlocityRecordSObjectType": "%vlocity_namespace%__PicklistValue__c",
        "VlocityRecordSourceKey": "%vlocity_namespace%__PicklistValue__c/94b3c3e7-6b1b-f00b-eabc-3490b7b372c2"
    }
]